burndown_chart_generator/__init__.py
burndown_chart_generator/__main__.py
burndown_chart_generator/_version.py
burndown_chart_generator/glyph_types_generator.py
burndown_chart_generator-0.1.1.dist-info/LICENSE
burndown_chart_generator-0.1.1.dist-info/METADATA
burndown_chart_generator-0.1.1.dist-info/WHEEL
burndown_chart_generator-0.1.1.dist-info/entry_points.txt
burndown_chart_generator-0.1.1.dist-info/top_level.txt
burndown_chart_generator-0.1.1.dist-info/RECORD
