Metadata-Version: 2.1
Name: burndown-chart-generator
Version: 0.1.1
Summary: A burndown chart generator for font projects, based on color marks
Author-email: Dalton Maag Ltd <sd@daltonmaag.com>
License: Apache-2.0
Project-URL: Repository, https://github.com/googlefonts/font-burndown-chart-generator
Requires-Python: >=3.10
License-File: LICENSE
Requires-Dist: attrs >=23.1
Requires-Dist: cattrs >=23.1
Requires-Dist: fontTools
Requires-Dist: matplotlib
Requires-Dist: pyyaml
Requires-Dist: toml
Requires-Dist: ufoLib2
